.gitignore
LICENSE
README.md
pyproject.toml
setup.py
demo/index.jinja2
demo/package.json
demo/run.py
demo/yarn.lock
src/jinja2_importmap/__init__.py
src/jinja2_importmap/__main__.py
src/jinja2_importmap/_version.py
src/jinja2_importmap/core.py
src/jinja2_importmap/ext.py
src/jinja2_importmap.egg-info/PKG-INFO
src/jinja2_importmap.egg-info/SOURCES.txt
src/jinja2_importmap.egg-info/dependency_links.txt
src/jinja2_importmap.egg-info/entry_points.txt
src/jinja2_importmap.egg-info/requires.txt
src/jinja2_importmap.egg-info/top_level.txt