Metadata-Version: 2.1
Name: jinja2-importmap
Version: 0.2.2
Summary: Configurable generation of importmaps, from Jinja2, Python, or shell.
License: Copyright (c) 2023, Dylan A. Lukes
Project-URL: repository, https://github.com/DylanLukes/jinja2-importmap
Keywords: jinja2,importmap,import-map
Classifier: Development Status :: 4 - Beta
Classifier: Environment :: Console
Classifier: Environment :: Web Environment
Classifier: Intended Audience :: Developers
Classifier: License :: OSI Approved :: BSD License
Classifier: Operating System :: OS Independent
Classifier: Programming Language :: Python :: 3
Classifier: Programming Language :: Python :: 3.8
Classifier: Programming Language :: Python :: 3.9
Classifier: Programming Language :: Python :: 3.10
Classifier: Programming Language :: Python :: 3.11
Classifier: Programming Language :: Python :: 3.12
Classifier: Topic :: Software Development :: Libraries :: Python Modules
Classifier: Topic :: Utilities
Requires-Python: >=3.8
License-File: LICENSE
